alisoam_openbaton_ems-1.1.3rc5.data/scripts/add-upstart-ems
ems/__init__.py
ems/ems.py
ems/receiver.py
ems/utils.py
alisoam_openbaton_ems-1.1.3rc5.dist-info/LICENSE
alisoam_openbaton_ems-1.1.3rc5.dist-info/METADATA
alisoam_openbaton_ems-1.1.3rc5.dist-info/WHEEL
alisoam_openbaton_ems-1.1.3rc5.dist-info/entry_points.txt
alisoam_openbaton_ems-1.1.3rc5.dist-info/top_level.txt
alisoam_openbaton_ems-1.1.3rc5.dist-info/RECORD
