Metadata-Version: 2.1
Name: alisoam-openbaton-ems
Version: 1.1.3rc5
Summary: Openbaton generic EMS
Home-page: https://github.com/AliSoAm/ems
Author: Openbaton
Author-email: ali.sorouramini@gmail.com
License: Apache 2.0
Keywords: python ems vnfm openbaton open baton
Platform: UNKNOWN
Classifier: Development Status :: 4 - Beta
Classifier: Intended Audience :: Developers
Classifier: Topic :: Software Development
Classifier: License :: OSI Approved :: Apache Software License
Requires-Dist: pika
Requires-Dist: gitpython
Requires-Dist: pyyaml
